leetcode_tester/__init__.py
leetcode_tester/structures.py
leetcode_tester/tester.py
leetcode_tester-1.0.7.dist-info/LICENSE
leetcode_tester-1.0.7.dist-info/METADATA
leetcode_tester-1.0.7.dist-info/WHEEL
leetcode_tester-1.0.7.dist-info/top_level.txt
leetcode_tester-1.0.7.dist-info/RECORD
