Metadata-Version: 2.1
Name: leetcode-tester
Version: 1.0.7
Summary: Local tester for Leetcode.
Home-page: https://github.com/devgum/leetcode_tester
Author: Devgum
Author-email: devgum@foxmail.com
License: UNKNOWN
Platform: UNKNOWN
Classifier: Programming Language :: Python :: 3.6
Classifier: License :: OSI Approved :: MIT License
Classifier: Operating System :: OS Independent
Requires-Python: >=3.6.0
